amane/__init__.py
amane/const.py
amane/db.py
amane/log.py
amane/skelton.py
amane/cmd/__init__.py
amane/cmd/ctl.py
amane/cmd/reporter.py
amane/cmd/reviewer.py
amane/cmd/smtpd.py
amane/tests/__init__.py
amane/tests/fake_db.py
amane/tests/fake_object.py
amane/tests/fake_smtpd.py
amane/tests/test_ctl.py
amane/tests/test_db.py
amane/tests/test_reporter.py
amane/tests/test_reviewer.py
amane/tests/test_smtpd.py
amane-1.0.1.dist-info/DESCRIPTION.rst
amane-1.0.1.dist-info/METADATA
amane-1.0.1.dist-info/RECORD
amane-1.0.1.dist-info/WHEEL
amane-1.0.1.dist-info/entry_points.txt
amane-1.0.1.dist-info/metadata.json
amane-1.0.1.dist-info/pbr.json
amane-1.0.1.dist-info/top_level.txt
