Metadata-Version: 2.0
Name: amane
Version: 1.0.1
Summary: Instant Mailing List Manager for Support Centers
Home-page: https://github.com/yosshy/amane
Author: Akira Yoshiyama
Author-email: akirayoshiyama@gmail.com
License: UNKNOWN
Platform: UNKNOWN
Classifier: Environment :: Console
Classifier: Intended Audience :: Information Technology
Classifier: Intended Audience :: System Administrators
Classifier: License :: OSI Approved :: Apache Software License
Classifier: Operating System :: POSIX :: Linux
Classifier: Programming Language :: Python
Classifier: Programming Language :: Python :: 3
Classifier: Programming Language :: Python :: 3.4
Requires-Dist: email-normalize
Requires-Dist: jinja2
Requires-Dist: pbr
Requires-Dist: pymongo
Requires-Dist: yaml
